villa_python_sdk/__init__.py
villa_python_sdk/calculator.py
villa_python_sdk/py.typed
villa_python_sdk/types.py
villa_python_sdk-0.1.0rc5.dist-info/LICENSE
villa_python_sdk-0.1.0rc5.dist-info/METADATA
villa_python_sdk-0.1.0rc5.dist-info/WHEEL
villa_python_sdk-0.1.0rc5.dist-info/top_level.txt
villa_python_sdk-0.1.0rc5.dist-info/RECORD
