Metadata-Version: 2.2
Name: villa-python-sdk
Version: 0.1.0rc5
Summary: an sdk for managing villa ecommerce attributes
Author-email: nic <nwanavit@gmail.com>
License: Apache Software License 2.0
Project-URL: Bug Tracker, https://github.com/thanakijwanavit/villa-python-sdk/issues
Project-URL: Changelog, https://github.com/thanakijwanavit/villa-python-sdk/blob/main/CHANGELOG.md
Project-URL: repository, https://github.com/thanakijwanavit/villa-python-sdk
Classifier: Development Status :: 2 - Pre-Alpha
Classifier: Intended Audience :: Developers
Classifier: Natural Language :: English
Classifier: Operating System :: OS Independent
Classifier: Programming Language :: Python :: 3.9
Classifier: Programming Language :: Python :: 3.10
Classifier: Programming Language :: Python :: 3.11
Classifier: Programming Language :: Python :: 3.12
Classifier: Programming Language :: Python :: 3.13
Classifier: Topic :: Software Development :: Libraries
Requires-Python: >=3.9
License-File: LICENSE
Requires-Dist: boto3>=1.34.0
